{
  "GENERAL": {
    "TABLE": {
      "DELETE": "حذف"
    },
    "VIEW": "نمایش",
    "UPDATE": "ویرایش",
    "CREATE": "ایجاد",
    "NEW": "جدید",
    "MAIN_INFO": "اطلاعات اصلی",
    "ACTION": "عملیات",
    "APPLICATION": "وب اپلیکیشن نگهداری و تعمیرات CMMS",
    "HELP": "راهنما",
    "SEARCH": "جستجو",
    "LOGOUT": "خروج از سامانه",
    "USER_PROFILE": "پروفایل کاربری",
    "SAVE": "ثبت",
    "UPLOAD": "بارگذاری",
    "FORM_RESET": "بارکذاری مجدد فرم",
    "ERROR": "خطای سمت سرور. لطفا با مدیر سیستم تماس بگیرید.",
    "DELETE": "حذف",
    "CANCEL": "بستن",
    "CONFIRM": "تایید",
    "SEARCH_IN_TREE": "جستجو در درختواره",
    "HEADER_USER": "کاربر :",
    "EXIT": "خروج از سامانه",
    "YES": "بله",
    "NO": "خیر",
    "HAS": "دارد",
    "HAS_NOT": "ندارد",
    "UNDERSTAND": "متوجه شدم",
    "ROW": "تعداد کل رکورد ها",
    "SIZE": "تعداد رکورد ها در صفحه",
    "CURRENT": " صفحه جاری",
    "HISTORY": "تاریخچه",
    "ACTIVE": "فعال",
    "INACTIVE": "غیر فعال",
    "SHOW_HISTORY_DETAILS": "نمایش جزییات ",
    "NOT_FOUND_MESSAGE": "داده ای جهت نمایش وجود ندارد.",
    "LOADING": "در حال بارگذاری",
    "UPLOAD_IMAGE": "تصویر",
    "PERCENT": "درصد",
    "DESCRIPTION": "توضیحات",
    "ASSET_SELECT": "انتخاب دارایی",
    "EMPLACEMENT_SELECT": "انتخاب محل استقرار",
    "EVENT": {
      "TITLE": "تاریخچه",
      "UPDATE": " ویرایش",
      "VIEW": "نمایش ",
      "INSERT": "ایجاد ",
      "DELETE": "حذف ",
      "DONE": "شد",
      "REJECT_CONFIRM": "برگشت از تایید",
      "REJECTED": "رد درخواست",
      "CONFIRM": "تایید",
      "EXECUTION": "اجرا",
      "RETURN_EXECUTION": "بازگشت از اجرا",
      "UNDERSTAND": "متوجه شدم",
      "FINISH": "خاتمه یافته",
      "REJECT_CALCULATION": "بازگشت از محاسبه",
      "THERE_IS_NO_HISTORY": "تاریخچه ای یافت نشد."
    },
    "BUTTON": {
      "ROW_SELECTOR": "انتخاب گر سطر",
      "COLUMN_SELECTOR": "انتخاب گر ستون",
      "SEND_TO_EXCEL": "ارسال به اکسل",
      "PRINT": "چاپ",
      "BACK_TO_LIST": "بازگشت",
      "EDIT": "ویرایش",
      "DELETE": "حذف"
    },
    "PREVENTIVE": "پیشگیرانه",
    "PERIOD": "دوره‌ای",
    "NOT_ACCEPT": "تایید نشده",
    "DISPLAY_PRIORITY": "اولویت نمایش",
    "SETTINGS": "تنظیمات",
    "SHOW_CARD": "نمایش کارت",
    "HOUR": "ساعت",
    "MINUTE": "دقیقه",
    "SECOND": "ثانیه",
    "AND": "و",
    "ERROR_TITLE": "خطا",
    "WARNING_TITLE": "توجه",
    "SUCCESS_TITLE": "تایید",
    "INFO_TITLE": "اطلاعیه"
  },
  "DATATABLE": {
    "EDIT": "ویرایش",
    "DELETE": "حذف",
    "TOTAL_RECORD": " مورد",
    "EMPTY_RECORD": "داده ای  برای نمایش موجود نیست. ",
    "SELECTED_MESSAGE": "داده انتخاب شده است",
    "RECORD": "رکورد",
    "FROM": "از",
    "FIRST_PAGE": "صفحه اول",
    "LAST_PAGE": "صفحه آخر",
    "NEXT_PAGE": "صفحه بعد",
    "PREVIOUS_PAGE": "صفحه قبل",
    "ROW_NUMBER": "ردیف",
    "ACTION": "عملیات",
    "CREATED": "تاریخ ایجاد",
    "UPDATED": "تاریخ آخرین ویرایش",
    "CREATED_BY": "ایجاد کننده",
    "UPDATED_BY": " آخرین ویرایش کننده",
    "VIEW": "مشاهده کاربر",
    "ACTIVE_INACTIVE": "فعال / غیر فعال کردم کاربر"
  },
  "WEEKDAY": {
    "MONDAY": "دوشنبه",
    "TUESDAY": "سه شنبه",
    "WEDNESDAY": "چهارشنبه",
    "THURSDAY": "پنج شنبه",
    "FRIDAY": "جمعه",
    "SATURDAY": "شنبه",
    "SUNDAY": "یک شنبه"
  },
  "CURRENCY": {
    "RIAL": "ریال",
    "DOLLAR": "دلار",
    "EURO": "یورو",
    "DURHAM": "درهم",
    "MILLION_RIALS": "میلیون ریال",
    "THOUSANDS": "هزار",
    "MILLIONS": "میلیون",
    "BILLIONS": "میلیارد",
    "TRILLIONS": "تریلیون",
    "QUADRILLIONS": "کوادریلیون"
  },
  "ATTACHMENT": {
    "UPLOAD_TITLE": "پیوست تصویر",
    "VIEW_TITLE": "پیوست تصویر",
    "UPLOAD": "بارگزاری",
    "SUCCESS": "بارگذاری با موفقیت انجام شد.",
    "ERROR": "خطا در بارگذاری اطلاعات . لطفا دوباره سعی کنید و یا با مدیر سیستم تماس بگیرید",
    "DROPZONE": {
      "TITLE": "فایل مورد نظر را کشیده و در اینحا رها کنید",
      "OR": "یا",
      "BROWS": "انتخاب فایل"
    },
    "CROPPER": {
      "CROP": "برش تصویر",
      "CANCEL": "لغو"
    },
    "PREVIEW_CARD": {
      "REMOVE": "حذف",
      "UPLOAD_ERROR": "بارگذاری با مشکل مواجه شده است . لطفا دوباره سعی کنید و یا با مدیر سیستم تماس بگیرید"
    }
  },
  "MESSAGES": {
    "BACK_TO_LIST_TITLE": "بازگشت به لیست",
    "BACK_TO_LIST": "آیا از بازگشت به لیست اطمینان دارید ؟",
    "IS_NOT_DELETABLE": "امکان حذف این داده وجود ندارد",
    "NOT_FOUND": "داده ای پیدا نشد",
    "DUPLICATE_CODE": "کد وارد شده تکراری است.",
    "DUPLICATE_NAME": "عنوان  وارد شده تکراری است.",
    "SERVER_ERROR": "خطا در برقراری ارتباط با سرور",
    "NUMBER_VALIDATION": "مقدار عددی وارد کنید",
    "MAXLENGTH_MUST_BE_15": "حداکثر 15 کاراکتر مجاز است.",
    "NUMBER_SHOULD_BE_BETWEEN_ZERO_TO_HUNDRED": "مقدار باید بین ۰ تا ۱۰۰ باشد.",
    "DISCOUNT_OVER_THAN_PRICE": "مبلغ تخفیف بیشتر از مقدار مجاز است.",
    "WAREHOUSE_COULD_NOT_DELETE": "برای این انبار یک دسته انبار تعریف شده و امکان حذف وجود ندارد.",
    "CATEGORY_WITH_SAME_NAME_EXIST": "یک دسته انبار با این نام قبلا برای این انبار تعریف شده است.",
    "CATEGORY_COULD_NOT_DELETE": "از این دسته انبار در تعریف کالا استفاده شده است.",
    "GOODS_WITH_SAME_NAME_OR_CODE_ALREADY_EXIST": "کالا با این نام و کد قبلا تعریف شده است .",
    "WAREHOUSE_WITH_SAME_NAME_EXIST": "انبار با این نام  تعریف شده است .",
    "ACCOUNT_COULD_NOT_DELETE_BECAUSE_HAS_CHILD": "این حساب دارای حساب دارای زیر مجموعه است و امکان حذف آن نیست.",
    "ACTIVE_FINANCIAL_YEAR_EXIST": "سال مالی فعال وجود دارد",
    "FINANCIAL_YEAR_INVALID_PERIOD_EXCEPTION": "تاریخ پایان سال مالی باید حداقل یک روز و حداکثر 365(سال کبیسه 366) روز از تاریخ شروع سال مالی بیشتر باشد.",
    "FINANCIAL_YEAR_IN_USE_AND_NOT_DELETABLE": "این سال مالی درحال استفاده بوده و امکان حذف وجود ندارد",
    "FINANCIAL_YER_IN_USE_AND_NOT_EDITABLE": "این سال مالی درحال استفاده بوده و امکان ویرایش وجود ندارد",
    "THERE_IS_A_FINANCIAL_YEAR_IN_THIS_PERIOD": "در این بازه زمانی سال مالی وجود داشته و امکان ایجاد سال مالی دیگر در این بازه زمانی امکان پذیر نیست ",
    "ACCOUNT_COULD_NOT_EDIT": "این حساب قابل ویرایش نمی باشد",
    "FINANCIAL_YEAR_END_DATE_IS_BEFORE_START_DATE": "تاریخ پایان سال مالی نمی تواند قبل از شروع سال مالی باشد",
    "TITLE1_DUPLICATE": "عتوان اول تکراری است",
    "FINANCIAL_YEAR_START_DATE_IS_AFTER_END_DATE": "تاریخ شروع سال مالی نمی تواند بعد از شروع پایان مالی باشد",
    "FINANCIAL_YEAR_IS_NOT_EDITABLE": " سال مالی قابل ویرایش نیست",
    "FINANCIAL_YEAR_IS_NOT_DELETABLE": "تاریخ شروع به جز سال اول، سیستمی هست و قابل ویرایش نیست کلا",
    "CHEQUE_BOOK_SAME_NUMBER": "شماره شروع و پایان تعریف شده برای چک صحیح نیست. برای این بانک در این بازه قبلا دسته چک تعربف شده و امکان ایحاد برگه چک تکراری وجود دارد.",
    "CHEQUE_BOOK_START_NUMBER": "سریال شروع و پایان نمی تواند ۰ باشد",
    "DISCOUNT_APPLIED_ALL_ITEMS": "مبلغ تخفیف کلی بر روی همه اقلام، اعمال می شود.",
    "DISCOUNT_LINE_DELETED": "در صورت اعمال تخفیف کلی، تخفیف های هر سطر پاک می شود.",
    "DISCOUNT_TOTAL_GOES_UP_DOWN": "مبلغ تخفیف به بالا و پایین رُند می شود.",
    "DISCOUNT_GOES_UP_DOWN": "در صورت استفاده از درصد تخفیف، مبلغ تحفیف به بالا و پایین رند می شود",
    "PROPERTIES_AND_FIXES_ASSETS_NOT_FOUND": "اموال و دارایی های ثابت یافت نشد.",
    "LEVEL_CODE_INVALID_EXCEPTION": "کد طبقه نامعتبر است.",
    "GROUP_CODE_INVALID_EXCEPTION": "کد گروه نامعتبر است.",
    "LEVEL_IS_NOT_UPDATABLE": "این طبقه قابل بروزرسانی نیست.",
    "GROUP_IS_NOT_UPDATABLE": "این گروه قابل بروزرسانی نیست.",
    "LEVEL_IS_NOT_DELETABLE_EXCEPTION": "این طبقه به علت داشتن زیرشاخه(گروه) قابل حذف نیست",
    "GROUP_IS_NOT_DELETABLE": "این گروه به علت استفاده شدن در فرم تحصیل دارایی قابل حدف نیست",
    "SAVE_SUCCESSFUL": "ثبت با موفقیت انجام شد",
    "DELETE_SUCCESSFUL": "حذف با موفقیت انجام شد",
    "UPDATE_SUCCESSFUL": "ثبت با موفقیت انجام شد",
    "UPDATE": "ویرایش با موفقیت انجام شد",
    "DELETE_EMPLACEMENT_LOCATION_NOT_POSSIBLE": "این محل استقرار قابل حدف نیست",
    "EMPLACEMENT_CODE_INVALID_EXCEPTION": "کد محل استقرار نامعتبر است.",
    "EMPLACEMENT_CODE_REQUIRED": "کد محل استقرار الزامی است.",
    "EMPLACEMENT_NAME_REQUIRED": "نام محل استقرار الزامی است.",
    "NAME_DUPLICATE_EXCEPTION": "نام وارد شده تکراری است",
    "NAME_UNIQUE_EXCEPTION": "نام وارد شده تکراری است",
    "CODE_DUPLICATE_EXCEPTION": "کد وارد شده تکراری است",
    "LEVEL_WITH_SAME_NAME_IS_EXIST": "نام وارد شده تکراری است",
    "WAREHOUSE_WITH_INVOICE_IS_ALREADY_EXIST": "برای این فاکتور فروش، قبلا حواله خروج صادر شده است.",
    "SALARY_WITH_SAME_STAFF_ALREADY_EXIST": "برای این کارمند قبلا دستمزد تعریف شده است",
    "OBJECT_IS_NOT_DELETABLE_EXCEPTION": "این مورد قابل حذف نیست.",
    "OVERLAP_DATE_EXCEPTION": "تاریخ همخوانی ندارد.",
    "ENTER_ALL_MANDATORY_FIELD": "ابتدا فیلد های اجباری رو پر کنید.",
    "ENTER_ALL_PERMISSION": " برای این کاربر هیچ دسترسی تعریف نشده است.",
    "END_DATE_IS_BEFORE_START_DATE": "تاریخ پایان باید بعد از تاریخ شروع باشد.",
    "START_DATE_IS_AFTER_END_DATE": "تاریخ شروع نمی تواند بعد از تاریخ پایان باشد.",
    "USER_NAME_UNIQ": "کاربری با این نام کاربری قبلا تعریف شده است .",
    "NOT_ADMIN_USER": "امکان تعریف کاربری با نام کاربری که شامل عبارت 'admin' باشد  نیست .",
    "WAGE_OVERLAP_DATE": "دستمزد های تعریف شده برای این کاربر دارای همپوشانی زمانی است و امکان محاسبه هزینه برای کاربر نیست . ",
    "USERNAME_NOT_FOUND_EXCEPTION": "کاربری با این نام کاربری وجود ندارد.",
    "PASSWORD_INCORRECT_EXCEPTION": "رمز عبور اشتباه است.",
    "USER_IS_LOCK_OR_IS_IN_ACTIVE": "حساب کاربری شما غیر فعال شده است. لطفا با مدیر سامانه تماس بگیرد.",
    "USER_HAS_NO_PERMISSION": "برای این کاربر دسترسی تعریف نشده است. لطفا با مدیر سامانه تماس بگیرید.",
    "ERROR_FORBIDDEN": "خطای دسترسی. لطفا با مدیر سامانه تماس بگیرید.",
    "INVALID_MOBILE": "شماره همراه وارد شده صحیح نیست.",
    "INVALID_NATIONAL_CODE": "کد ملی وارد شده صحیح نیست.",
    "EMAIL_INVALID": "ایمیل وارد شده صحیح نیست.",
    "NOT_DELETABLE_EXCEPTION": " امکان حذف این رکورد وجود ندارد.",
    "DELETE_CONFIRM": " آیا از حذف رکورد اطمینان دارید ؟ ",
    "SESSION_EXPIRED": "زمان کاربری شما پایان یافته است. لطفا دوباره وارد سیستم شوید",
    "NOT_FOUND_EXCEPTION": "موردی یافت نشد.",
    "NOT_UPDATABLE_EXCEPTION": "امکان ویرایش وجود ندارد.",
    "PART_IS_NOT_DELETABLE_USING_IN_WORK_LOG": "امکان حذف این قطعه به علت استفاده در ثبت علکرد وجود ندارد"
  },
  "SHARE_COMPONENT": {
    "CREATE_NEW_ACCOUNT": "ایجاد حساب جدید",
    "ACCOUNT_TITLE": "عنوان",
    "ACCOUNT_CODE": "کد",
    "CREATE_NEW_LEVEL": "ایجاد کلاس جدید",
    "CREATE_NEW_GROUP": "ایجاد گروه جدید",
    "CREATE_NEW_GOODS": "ایجاد کالای جدید",
    "CREATE_NEW_PERSON": "ایجاد شخص جدید",
    "CREATE_NEW_ASSET": "ایجاد دارایی جدید",
    "CREATE_NEW_FAILURE_MODE": "ایجاد حالت خرابی جدید",
    "CREATE_NEW_FAILURE_DETECTION": "ایجاد روش کشف خرابی جدید",
    "CREATE_NEW_COST_CENTER": "تعریف مرکز‌هزینه جدید",
    "CREATE_NEW_WORK_CENTER": "تعریف مرکز‌کاری جدید",
    "CREATE_NEW_PRODUCTION_LINE": "تعریف خط‌تولید جدید",
    "CREATE_NEW_EMPLACEMENT_LOCATION": "تعربف محل استقرار جدید"
  },
  "DASHBOARD": {
    "CARTABLE": "نمایش کارتابل",
    "ORDER_NUMBER": "تعداد سفارشات",
    "PRE_INVOICE": "تعداد پیش فاکتورها تا این لحظه"
  },
  "FILTER": {
    "FROM": "از",
    "TO": "تا",
    "DATE_OF_CREATE": "تاریخ ایجاد",
    "DATE_OF_EDIT": "تاریخ ویرایش",
    "CREATOR": "ایجاد کننده",
    "EDITOR": "ویرایش کننده",
    "DELETE_ALL_FILTER": "حذف همه",
    "FILTER": "فیلتر"
  },
  "PRIORITY": {
    "CRITICAL": "اضطراری",
    "HIGH": "فوری",
    "MIDDLE": "جدی",
    "LOW": "نرمال"
  },
  "KANBAN": {
    "TITLE": "عنوان",
    "ASSIGNEE": "مسول اجرا",
    "STATUS": "وضعیت",
    "AUTHOR": "ایجاد کننده",
    "NUMBER": "کد",
    "PRIORITY": "اولویت انجام",
    "START_DATE": "تاریخ شروع",
    "END_DATE": "تاریخ پایان",
    "ID": "شماره",
    "MORE_INFO": "نمایش بیشتر",
    "DOING_TIME_PASSED": "زمان انجام گذشته"
  },
  "KANBAN_CARD_MENU": {
    "ARCHIVE": "آرشیو",
    "DELETE": "حذف",
    "EDIT": "ویرایش",
    "PRINT": "چاپ"
  },
  "KANBAN_BOARD_COLUMN": {
    "OPEN": "باز",
    "UNDER_EXECUTION": "در حال اجرا",
    "WORK_LOG": "ثبت عملکرد",
    "FINISHED": "خاتمه یافته"
  },
  "CALENDAR": {
    "TODAY": "امروز",
    "MONTH": "ماه",
    "WEEK": "هفته",
    "DAY": "روز",
    "LIST": "لیست",
    "MORE": "بیشتر"
  },
  "PERSON_TYPE": {
    "STAFF": "کارمند",
    "SUPPLIER": "تامین کننده",
    "CONTRACTOR": "پیمانکار"
  },
  "LOGIN": {
    "USERNAME": "نام کاربری",
    "PASSWORD": "کلمه عبور",
    "SUBMIT": "ورود"
  },
  "EVENTS": {
    "CODE": "کد خطا",
    "MESSAGE": "پیغام خطا",
    "ERROR_TIME": "زمان وقوع خطا",
    "TABLE": {
      "PLACE_HOLDER": "کد خطا را جهت  جستجوی خطای مورد نظر وارد کنید"
    }
  }
}
